gptfunction/GPTFunction.py
gptfunction/__init__.py
gptfunction-0.2.0.dist-info/LICENSE.md
gptfunction-0.2.0.dist-info/METADATA
gptfunction-0.2.0.dist-info/WHEEL
gptfunction-0.2.0.dist-info/top_level.txt
gptfunction-0.2.0.dist-info/RECORD
