Metadata-Version: 2.1
Name: gptfunction
Version: 0.2.0
Summary: A decorator for wrapping Python functions to generate an OpenAI GPT function calling schema.
Author: PandasAreBears
License: Copyright (c) 2023 PandasAreBears
Project-URL: Homepage, https://github.com/PandasAreBears/gpt_function
Keywords: openai,gpt,function calling
Requires-Python: >=3.5
License-File: LICENSE.md
Requires-Dist: docstring-parser
